CHANGELOG.txt
LICENSE.txt
MANIFEST.in
setup.cfg
setup.py
test/test_api.py
test/test_connection.py
test/test_cursor.py
test/test_group.py
test/test_predictions.py
test/test_related.py
test/test_similar.py
test/test_tables.py
test/test_utils.py
veritable/__init__.py
veritable/api.py
veritable/connection.py
veritable/cursor.py
veritable/exceptions.py
veritable/utils.py
veritable/version.py
veritable.egg-info/PKG-INFO
veritable.egg-info/SOURCES.txt
veritable.egg-info/dependency_links.txt
veritable.egg-info/requires.txt
veritable.egg-info/top_level.txt