Metadata-Version: 1.1
Name: veritable
Version: 0.9.9pre138
Summary: Python Client Library for Veritable API
Home-page: http://dev.priorknowledge.com/
Author: Max Gasner
Author-email: max@priorknowledge.com
License: MIT
Platform: any
Classifier: Development Status :: 5 - Production/Stable
Classifier: Intended Audience :: Developers
Classifier: License :: OSI Approved :: MIT License
Classifier: Operating System :: OS Independent
Classifier: Programming Language :: Python :: 2.6
Classifier: Programming Language :: Python :: 2.7
Classifier: Programming Language :: Python :: 3.1
Classifier: Topic :: Database
Classifier: Topic :: Scientific/Engineering :: Information Analysis
